medren/__init__.py
medren/__main__.py
medren/backend_piexif.py
medren/backends.py
medren/consts.py
medren/datetime_from_filename.py
medren/exif_process.py
medren/geocode.py
medren/gui_fsg.py
medren/profiles.py
medren/renamer.py
medren/timezone_offset.py
medren/util.py
medren-0.5.0.dist-info/entry_points.txt
medren-0.5.0.dist-info/LICENSE
medren-0.5.0.dist-info/METADATA
medren-0.5.0.dist-info/WHEEL
medren-0.5.0.dist-info/RECORD
