Metadata-Version: 2.3
Name: medren
Version: 0.5.0
Summary: MedRen - The Media Renamer
Author: Idan Miara
Author-email: idan@miara.com
Requires-Python: >=3.10,<4.0
Classifier: Programming Language :: Python :: 3
Classifier: Programming Language :: Python :: 3.10
Classifier: Programming Language :: Python :: 3.11
Classifier: Programming Language :: Python :: 3.12
Classifier: Programming Language :: Python :: 3.13
Requires-Dist: exifread (<3)
Requires-Dist: ffmpeg-python (>=0.2.0,<0.3.0)
Requires-Dist: freesimplegui (>=5.2.0.post1,<6.0.0)
Requires-Dist: geopy (>=2.4.1,<3.0.0)
Requires-Dist: hachoir (>=3.3.0,<4.0.0)
Requires-Dist: openlocationcode (>=1.0.1,<2.0.0)
Requires-Dist: piexif (>=1.1.3,<2.0.0)
Requires-Dist: pyexiftool (>=0.5.6,<0.6.0)
Requires-Dist: pymediainfo (>=7.0.1,<8.0.0)
Requires-Dist: pyperclip (>=1.8.2,<2.0.0)
Requires-Dist: timezonefinder (>=6.5.9,<7.0.0)
Requires-Dist: tzdata (>=2025.2,<2026.0)
Project-URL: Homepage, https://github.com/idanmiara/medren
Project-URL: Repository, https://github.com/idanmiara/medren.git
